{
  "id": 26,
  "title": {
    "fr": "Simulation Complète d’Entreprise (Cas Réel Structuré)",
    "en": "Full Business Simulation (Structured Real Case)",
    "ar": "محاكاة أعمال كاملة (حالة حقيقية منظمة)"
  },
  "content": {
    "fr": {
      "objectif": "Appliquer toutes les notions comptables dans un cas réel structuré et comprendre le fonctionnement global d’une entreprise.",

      "explication": "🔹 1. Création de l’entreprise\nCapital = 50000\n\nÉcriture:\nBanque Dr 50000\nTo Capital 50000\n\n\n🔹 2. Opérations du mois\n\n1. Achat marchandises à crédit = 20000 + TVA 20%\n2. Vente = 40000 (50% cash, 50% crédit)\n3. Paiement loyer = 5000\n4. Salaire = 8000\n5. Achat machine = 10000\n\n\n🔹 3. Journal\n\nAchat:\n6111 Dr 20000\n3455 TVA Dr 4000\n4411 Fournisseur Cr 24000\n\nVente:\nCaisse Dr 20000\nClients Dr 20000\nVentes Cr 33333\nTVA Cr 6667\n\nCharges:\nCharges Dr 13000\nBanque Cr 13000\n\nMachine:\nImmobilisation Dr 10000\nBanque Cr 10000\n\n\n🔹 4. Amortissement\nMachine = 10000\nTaux = 10%\nAmortissement = 1000\n\nÉcriture:\nCharge Dr 1000\nAmortissement Cr 1000\n\n\n🔹 5. Stock & COGS\nStock initial = 0\nAchat = 20000\nStock final = 5000\n\nCOGS = 15000\n\n\n🔹 6. Résultat (CPC)\nProduits = 33333\nCOGS = 15000\nCharges = 14000\n\nRésultat = 4333\n\n\n🔹 7. TVA\nTVA collectée = 6667\nTVA récupérable = 4000\n\nTVA à payer = 2667\n\n\n🔹 8. Cash Flow\nEntrées = 20000\nSorties = 23000\n\nCash = -3000\n\n\n🔹 9. Analyse\nProfit positif mais cash négatif\n\nProblème = ventes à crédit\n\n\n🔹 10. Décision\nAméliorer recouvrement clients\nRéduire dépenses\nÉviter crédit excessif",

      "imageUrl": "https://images.unsplash.com/photo-1556742044-3c52d6e88c62?q=80&w=1000&auto=format&fit=crop",

      "exemple": "Entreprise avec profit mais manque de cash = situation risquée",

      "pratique": "1. TVA collectée 8000 et récupérable 3000 → TVA ?\n2. Produits 30000, charges 20000 → résultat ?\n3. Pourquoi cash négatif ?",

      "reponses": "1 → 5000\n2 → 10000\n3 → ventes à crédit",

      "resume": "Cycle complet maîtrisé avec analyse et décision"
    },

    "en": {
      "objectif": "Apply full accounting system in a structured real case.",

      "explication": "Covers journal entries, depreciation, stock, tax and cash flow with final decision making.",

      "imageUrl": "https://images.unsplash.com/photo-1556742044-3c52d6e88c62?q=80&w=1000&auto=format&fit=crop",

      "exemple": "Profit positive but cash negative = risk",

      "pratique": "1. VAT?\n2. Profit?\n3. Why cash issue?",

      "reponses": "1 → 5000\n2 → 10000\n3 → credit sales",

      "resume": "Full system applied."
    },

    "ar": {
      "objectif": "تطبيق النظام المحاسبي الكامل في حالة عملية.",

      "explication": "يشمل اليومية، الإهلاك، المخزون، الضرائب والتدفق النقدي مع اتخاذ القرار.",

      "imageUrl": "https://images.unsplash.com/photo-1556742044-3c52d6e88c62?q=80&w=1000&auto=format&fit=crop",

      "exemple": "ربح إيجابي مع نقد سلبي = خطر",

      "pratique": "1. الضريبة؟\n2. الربح؟\n3. لماذا المشكلة؟",

      "reponses": "1 → 5000\n2 → 10000\n3 → البيع الآجل",

      "resume": "تم تطبيق النظام بالكامل."
    }
  },

  "practice_zone": {}
}